visionir_io_observer/__init__.py
visionir_io_observer/observer.py
visionir_io_observer-2024.6.6.dist-info/LICENSE
visionir_io_observer-2024.6.6.dist-info/METADATA
visionir_io_observer-2024.6.6.dist-info/WHEEL
visionir_io_observer-2024.6.6.dist-info/RECORD
