Metadata-Version: 2.1
Name: visionir_io_observer
Version: 2024.6.6
Summary: Observer class for logging and pyroscope-app
Home-page: https://github.com/visionir-io/visionir/tree/master/apps/observer
License: MIT
Author: Nir Abutbul
Author-email: nir@visionir.io
Requires-Python: >=3.11,<4.0
Classifier: License :: OSI Approved :: MIT License
Classifier: Programming Language :: Python :: 3
Classifier: Programming Language :: Python :: 3.11
Classifier: Programming Language :: Python :: 3.12
Project-URL: Repository, https://github.com/visionir-io/visionir/tree/master/apps/observer
